wxhandler/__init__.py
wxhandler/wxhandler.py
wxhandler-0.1.1.5.1.dist-info/LICENSE
wxhandler-0.1.1.5.1.dist-info/METADATA
wxhandler-0.1.1.5.1.dist-info/WHEEL
wxhandler-0.1.1.5.1.dist-info/top_level.txt
wxhandler-0.1.1.5.1.dist-info/RECORD
