Metadata-Version: 2.1
Name: wxhandler
Version: 0.1.1.5.1
Summary: A Python package for handling wxHandler operations.
Home-page: https://github.com/chenbifu/wxhandler
Author: chenbifu
Author-email: pythonaaa@gmail.com
Classifier: Programming Language :: Python :: 3
Classifier: License :: OSI Approved :: MIT License
Classifier: Operating System :: OS Independent
Requires-Python: >=3.10
License-File: LICENSE
Requires-Dist: requests
